collaborative_filtering/__init__.py
collaborative_filtering/dataset.py
collaborative_filtering/early_stop.py
collaborative_filtering/evaluate.py
collaborative_filtering/loss.py
collaborative_filtering/metrics.py
collaborative_filtering/parameters.py
collaborative_filtering/train.py
collaborative_filtering/utils.py
collaborative_filtering/model/__init__.py
collaborative_filtering/model/mf.py
collaborative_filtering/model/mlp.py
collaborative_filtering-0.0.7.dist-info/LICENSE
collaborative_filtering-0.0.7.dist-info/METADATA
collaborative_filtering-0.0.7.dist-info/WHEEL
collaborative_filtering-0.0.7.dist-info/top_level.txt
collaborative_filtering-0.0.7.dist-info/RECORD
