Metadata-Version: 2.1
Name: collaborative-filtering
Version: 0.0.7
Summary: A package for collaborative filtering recommendation
Home-page: https://github.com/yusanshi/collaborative-filtering
Author: yusanshi
Author-email: meet.leiyu@gmail.com
License: UNKNOWN
Project-URL: Bug Tracker, https://github.com/yusanshi/collaborative-filtering/issues
Platform: UNKNOWN
Classifier: Programming Language :: Python :: 3
Classifier: License :: OSI Approved :: MIT License
Classifier: Operating System :: POSIX :: Linux
Requires-Python: >=3.6
License-File: LICENSE
Requires-Dist: torch
Requires-Dist: pandas
Requires-Dist: numpy
Requires-Dist: tqdm
Requires-Dist: tensorboard
Requires-Dist: enlighten
Requires-Dist: coloredlogs
